odoo/addons/mail_autosubscribe/README.rst
odoo/addons/mail_autosubscribe/__init__.py
odoo/addons/mail_autosubscribe/__manifest__.py
odoo/addons/mail_autosubscribe/i18n/ca.po
odoo/addons/mail_autosubscribe/i18n/de.po
odoo/addons/mail_autosubscribe/i18n/es.po
odoo/addons/mail_autosubscribe/i18n/fr.po
odoo/addons/mail_autosubscribe/i18n/it.po
odoo/addons/mail_autosubscribe/i18n/mail_autosubscribe.pot
odoo/addons/mail_autosubscribe/models/__init__.py
odoo/addons/mail_autosubscribe/models/mail_autosubscribe.py
odoo/addons/mail_autosubscribe/models/mail_template.py
odoo/addons/mail_autosubscribe/models/mail_thread.py
odoo/addons/mail_autosubscribe/models/models.py
odoo/addons/mail_autosubscribe/models/res_partner.py
odoo/addons/mail_autosubscribe/readme/CONFIGURE.md
odoo/addons/mail_autosubscribe/readme/CONTRIBUTORS.md
odoo/addons/mail_autosubscribe/readme/DESCRIPTION.md
odoo/addons/mail_autosubscribe/readme/ROADMAP.md
odoo/addons/mail_autosubscribe/security/ir.model.access.csv
odoo/addons/mail_autosubscribe/static/description/icon.png
odoo/addons/mail_autosubscribe/static/description/index.html
odoo/addons/mail_autosubscribe/tests/__init__.py
odoo/addons/mail_autosubscribe/tests/test_mail_autosubscribe.py
odoo/addons/mail_autosubscribe/tests/models/__init__.py
odoo/addons/mail_autosubscribe/tests/models/fake_order.py
odoo/addons/mail_autosubscribe/views/mail_autosubscribe.xml
odoo/addons/mail_autosubscribe/views/mail_template.xml
odoo/addons/mail_autosubscribe/views/res_partner.xml
odoo_addon_mail_autosubscribe-18.0.1.1.0.4.dist-info/METADATA
odoo_addon_mail_autosubscribe-18.0.1.1.0.4.dist-info/WHEEL
odoo_addon_mail_autosubscribe-18.0.1.1.0.4.dist-info/top_level.txt
odoo_addon_mail_autosubscribe-18.0.1.1.0.4.dist-info/RECORD
