Metadata-Version: 2.1
Name: odoo-addon-mail_autosubscribe
Version: 18.0.1.1.0.4
Requires-Python: >=3.10
Requires-Dist: odoo==18.0.*
Summary: Automatically subscribe partners to its company's business documents
Home-page: https://github.com/OCA/mail
License: AGPL-3
Author: Camptocamp, Odoo Community Association (OCA)
Author-email: support@odoo-community.org
Classifier: Programming Language :: Python
Classifier: Framework :: Odoo
Classifier: Framework :: Odoo :: 18.0
Classifier: License :: OSI Approved :: GNU Affero General Public License v3
